sage_lib/AtomPositionManager.py
sage_lib/BandPathGenerator.py
sage_lib/BashScriptManager.py
sage_lib/BinaryDataHandler.py
sage_lib/ChargeFileManager.py
sage_lib/CrystalDefectGenerator.py
sage_lib/DFTEnsemble.py
sage_lib/DFTPartition.py
sage_lib/DFTSingleRun.py
sage_lib/FileManager.py
sage_lib/InputClassic.py
sage_lib/InputDFT.py
sage_lib/InputFileManager.py
sage_lib/KPointsManager.py
sage_lib/NonPeriodicSystem.py
sage_lib/OutFileManager.py
sage_lib/PeriodicSystem.py
sage_lib/PotentialManager.py
sage_lib/WaveFileManager.py
sage_lib/__init__.py
sage_lib/main.py
sage_lib/main2.py
sage_lib/main_rev.py
sage_lib/IO/BashScriptManager.py
sage_lib/IO/BinaryDataHandler.py
sage_lib/IO/ChargeFileManager.py
sage_lib/IO/DOSManager.py
sage_lib/IO/EigenvalueFileManager.py
sage_lib/IO/ForceFieldManager.py
sage_lib/IO/KPointsManager.py
sage_lib/IO/OutFileManager.py
sage_lib/IO/PROFileManager.py
sage_lib/IO/PotentialManager.py
sage_lib/IO/WaveFileManager.py
sage_lib/IO/__init__.py
sage_lib/IO/hybrid_db.py
sage_lib/IO/storage_backend.py
sage_lib/IO/input_handling_tools/InputClassic.py
sage_lib/IO/input_handling_tools/InputDFT.py
sage_lib/IO/input_handling_tools/InputDFTB.py
sage_lib/IO/input_handling_tools/InputFile.py
sage_lib/IO/input_handling_tools/InputFileManager.py
sage_lib/IO/input_handling_tools/__init__.py
sage_lib/IO/storage/__init__.py
sage_lib/IO/storage/backend.py
sage_lib/IO/storage/composite.py
sage_lib/IO/storage/hybrid.py
sage_lib/IO/storage/maintenance.py
sage_lib/IO/storage/memory.py
sage_lib/IO/storage/sqlite.py
sage_lib/IO/structure_handling_tools/AtomPosition.py
sage_lib/IO/structure_handling_tools/AtomPositionLoader.py
sage_lib/IO/structure_handling_tools/AtomPositionMaker.py
sage_lib/IO/structure_handling_tools/AtomPositionManager.py
sage_lib/IO/structure_handling_tools/AtomPositionOperator.py
sage_lib/IO/structure_handling_tools/NonPeriodicSystem.py
sage_lib/IO/structure_handling_tools/PeriodicSystem.py
sage_lib/IO/structure_handling_tools/__init__.py
sage_lib-0.1.6.64.dist-info/METADATA
sage_lib-0.1.6.64.dist-info/WHEEL
sage_lib-0.1.6.64.dist-info/entry_points.txt
sage_lib-0.1.6.64.dist-info/top_level.txt
sage_lib-0.1.6.64.dist-info/RECORD
