Metadata-Version: 2.1
Name: sage_lib
Version: 0.1.6.64
Summary: A library for advanced scientific calculations and visualization
Author: Lombardi, Juan Manuel
Author-email: lombardi@fhi-berlin.mpg.de
License: MIT
Keywords: scientific calculations visualization computational chemistry quantum mechanics machine learning data analysis
Requires-Dist: numpy >=1.21.0
Requires-Dist: tqdm >=4.50.0
Requires-Dist: joblib >=1.0.0
Requires-Dist: h5py >=3.6.0
Provides-Extra: all
Requires-Dist: Pillow ; extra == 'all'
Requires-Dist: PyOpenGL ; extra == 'all'
Requires-Dist: PyOpenGL-accelerate ; extra == 'all'
Requires-Dist: black ; extra == 'all'
Requires-Dist: coverage ; extra == 'all'
Requires-Dist: dscribe ; extra == 'all'
Requires-Dist: flake8 >=3.8 ; extra == 'all'
Requires-Dist: glfw ; extra == 'all'
Requires-Dist: hdbscan >=0.8.0 ; extra == 'all'
Requires-Dist: imageio >=2.10.0 ; extra == 'all'
Requires-Dist: imgui[glfw] ; extra == 'all'
Requires-Dist: kneed >=0.7.0 ; extra == 'all'
Requires-Dist: matplotlib >=3.4.0 ; extra == 'all'
Requires-Dist: mypy ; extra == 'all'
Requires-Dist: myst-parser ; extra == 'all'
Requires-Dist: pytest >=6.0 ; extra == 'all'
Requires-Dist: scikit-learn >=0.24.0 ; extra == 'all'
Requires-Dist: scipy >=1.7.0 ; extra == 'all'
Requires-Dist: seaborn >=0.11.0 ; extra == 'all'
Requires-Dist: sphinx-autodoc-typehints ; extra == 'all'
Requires-Dist: sphinx-rtd-theme >=0.5.0 ; extra == 'all'
Requires-Dist: sphinx >=4.0 ; extra == 'all'
Requires-Dist: tox ; extra == 'all'
Requires-Dist: umap-learn >=0.5.0 ; extra == 'all'
Provides-Extra: analysis
Requires-Dist: scipy >=1.7.0 ; extra == 'analysis'
Provides-Extra: dev
Requires-Dist: pytest >=6.0 ; extra == 'dev'
Requires-Dist: flake8 >=3.8 ; extra == 'dev'
Requires-Dist: black ; extra == 'dev'
Requires-Dist: mypy ; extra == 'dev'
Requires-Dist: coverage ; extra == 'dev'
Requires-Dist: tox ; extra == 'dev'
Provides-Extra: docs
Requires-Dist: sphinx >=4.0 ; extra == 'docs'
Requires-Dist: sphinx-rtd-theme >=0.5.0 ; extra == 'docs'
Requires-Dist: myst-parser ; extra == 'docs'
Requires-Dist: sphinx-autodoc-typehints ; extra == 'docs'
Provides-Extra: ml
Requires-Dist: scikit-learn >=0.24.0 ; extra == 'ml'
Requires-Dist: umap-learn >=0.5.0 ; extra == 'ml'
Requires-Dist: kneed >=0.7.0 ; extra == 'ml'
Requires-Dist: hdbscan >=0.8.0 ; extra == 'ml'
Requires-Dist: dscribe ; extra == 'ml'
Provides-Extra: viz
Requires-Dist: matplotlib >=3.4.0 ; extra == 'viz'
Requires-Dist: seaborn >=0.11.0 ; extra == 'viz'
Requires-Dist: imageio >=2.10.0 ; extra == 'viz'
Requires-Dist: glfw ; extra == 'viz'
Requires-Dist: PyOpenGL ; extra == 'viz'
Requires-Dist: PyOpenGL-accelerate ; extra == 'viz'
Requires-Dist: imgui[glfw] ; extra == 'viz'
Requires-Dist: Pillow ; extra == 'viz'
